nmgrid/__init__.py
nmgrid/__main__.py
nmgrid/config.py
nmgrid/main.py
nmgrid-0.0.1.dist-info/METADATA
nmgrid-0.0.1.dist-info/WHEEL
nmgrid-0.0.1.dist-info/licenses/LICENSE.txt
nmgrid-0.0.1.dist-info/RECORD
