Metadata-Version: 2.1
Name: nmgrid
Version: 0.0.1
Summary: The classic 2048 number grid game
Project-URL: Homepage, https://gitlab.com/RRkundkar777/ngrid
Project-URL: Documentation, https://gitlab.com/RRkundkar777/ngrid/-/blob/master/README.md?ref_type=heads
Project-URL: Issues, https://gitlab.com/RRkundkar777/ngrid/-/issues
Author-email: Rushikesh Kundkar <r4002001005025k@gmail.com>
License:                                  Apache License
License-File: LICENSE.txt
Keywords: 2048,game,number game
Classifier: Development Status :: 4 - Beta
Classifier: License :: OSI Approved :: Apache Software License
Classifier: Operating System :: OS Independent
Classifier: Programming Language :: Python
Classifier: Programming Language :: Python :: 3
Requires-Python: >=3.7
Requires-Dist: pygame>=2.1.2
